bookphucker/__init__.py
bookphucker/__main__.py
bookphucker/cli.py
bookphucker/commonvars.py
bookphucker/config.py
bookphucker/exc.py
bookphucker/jp.py
bookphucker/tw.py
bookphucker/utils.py
fuckbookwalker-0.1.3.dist-info/LICENSE
fuckbookwalker-0.1.3.dist-info/METADATA
fuckbookwalker-0.1.3.dist-info/WHEEL
fuckbookwalker-0.1.3.dist-info/entry_points.txt
fuckbookwalker-0.1.3.dist-info/RECORD
